{
  "default": {
      "vis-a-vis": "vis-à-vis",
      "v"       : "Vermes",
      "vermes"  : "Vermes",
      "Vermes"  : "Geza Vermes",
      "qumran"  : "Qumran",
      "jub"     : "Jubilees",
      "ga"      : "Genesis Apocryphon",
      "ant"     : "Jewish Antiquities",
      "lab"     : "Liber antiquitatum biblicarum",
      "rwb"     : "RwB",
      "RwB"     : "Rewritten Bible",
      "RWB"     : "Rewritten Bible",
      "rwB"     : "rewritten Bible",
      "dss"     : "Dead Sea Scrolls",
      "qumran"  : "Qumran",
      "sefer"   : "Sefer ha-Yashar",
      "pTarg"   : "Palestinian Targums",
      "2T"      : "Second Temple",
      "temple-scroll": "Temple Scroll"
  },
  "emph": {
      "stj-full": "Scripture and Tradition in Judaism: Haggadic Studies",
      "stj"     : "Scripture and Tradition"
  }
}
